baidutongji/__init__.py
baidutongji/api.py
baidutongji/data.py
baidutongji/metrics.py
baidutongji-0.1.6.dist-info/LICENSE
baidutongji-0.1.6.dist-info/METADATA
baidutongji-0.1.6.dist-info/WHEEL
baidutongji-0.1.6.dist-info/top_level.txt
baidutongji-0.1.6.dist-info/RECORD
