Metadata-Version: 2.1
Name: baidutongji
Version: 0.1.6
Summary: 百度统计 API Python 封装
Home-page: https://github.com/JeffersonQin/BaiduTongjiAPI
Author: JeffersonQin
Author-email: 1247006353@qq.com
License: MIT License
Keywords: stats,api,baidu
Platform: UNKNOWN
License-File: LICENSE
Requires-Dist: requests
